{
  "annotations": {
    "list": [
      {
        "builtIn": 1,
        "datasource": "-- Grafana --",
        "enable": true,
        "hide": true,
        "iconColor": "rgba(0, 211, 255, 1)",
        "name": "Annotations & Alerts",
        "type": "dashboard"
      }
    ]
  },
  "editable": true,
  "gnetId": null,
  "graphTooltip": 0,
  "id": null,
  "links": [],
  "panels": [
    {
      "datasource": "Prometheus",
      "fieldConfig": {
        "defaults": {
          "color": {
            "mode": "thresholds"
          },
          "mappings": [],
          "thresholds": {
            "mode": "absolute",
            "steps": [
              {
                "color": "green",
                "value": null
              },
              {
                "color": "red",
                "value": 80
              }
            ]
          },
          "unit": "dtdurations"
        },
        "overrides": []
      },
      "gridPos": {
        "h": 4,
        "w": 6,
        "x": 0,
        "y": 0
      },
      "id": 1,
      "options": {
        "colorMode": "value",
        "graphMode": "none",
        "justifyMode": "auto",
        "orientation": "auto",
        "reduceOptions": {
          "calcs": [
            "lastNotNull"
          ],
          "fields": "",
          "values": false
        },
        "text": {},
        "textMode": "auto"
      },
      "pluginVersion": "8.0.0",
      "targets": [
        {
          "expr": "sysUpTime{instance=\"192.168.1.1\",job=\"routeros\"} / 100",
          "refId": "A"
        }
      ],
      "title": "アップタイム",
      "type": "stat"
    },
    {
      "datasource": "Prometheus",
      "fieldConfig": {
        "defaults": {
          "color": {
            "mode": "thresholds"
          },
          "mappings": [],
          "thresholds": {
            "mode": "absolute",
            "steps": [
              {
                "color": "green",
                "value": null
              },
              {
                "color": "yellow",
                "value": 70
              },
              {
                "color": "red",
                "value": 85
              }
            ]
          },
          "unit": "percent",
          "min": 0,
          "max": 100
        },
        "overrides": []
      },
      "gridPos": {
        "h": 4,
        "w": 6,
        "x": 6,
        "y": 0
      },
      "id": 2,
      "options": {
        "colorMode": "value",
        "graphMode": "area",
        "justifyMode": "auto",
        "orientation": "auto",
        "reduceOptions": {
          "calcs": [
            "lastNotNull"
          ],
          "fields": "",
          "values": false
        },
        "text": {},
        "textMode": "auto"
      },
      "pluginVersion": "8.0.0",
      "targets": [
        {
          "expr": "avg(hrProcessorLoad{instance=\"192.168.1.1\",job=\"routeros\"})",
          "refId": "A"
        }
      ],
      "title": "CPU使用率",
      "type": "stat"
    },
    {
      "datasource": "Prometheus",
      "fieldConfig": {
        "defaults": {
          "color": {
            "mode": "thresholds"
          },
          "mappings": [],
          "thresholds": {
            "mode": "absolute",
            "steps": [
              {
                "color": "green",
                "value": null
              },
              {
                "color": "yellow",
                "value": 70
              },
              {
                "color": "red",
                "value": 85
              }
            ]
          },
          "unit": "percent",
          "min": 0,
          "max": 100
        },
        "overrides": []
      },
      "gridPos": {
        "h": 4,
        "w": 6,
        "x": 12,
        "y": 0
      },
      "id": 3,
      "options": {
        "colorMode": "value",
        "graphMode": "area",
        "justifyMode": "auto",
        "orientation": "auto",
        "reduceOptions": {
          "calcs": [
            "lastNotNull"
          ],
          "fields": "",
          "values": false
        },
        "text": {},
        "textMode": "auto"
      },
      "pluginVersion": "8.0.0",
      "targets": [
        {
          "expr": "(hrStorageUsed{instance=\"192.168.1.1\",job=\"routeros\",hrStorageIndex=\"65536\"} / hrStorageSize{instance=\"192.168.1.1\",job=\"routeros\",hrStorageIndex=\"65536\"}) * 100",
          "refId": "A"
        }
      ],
      "title": "メモリ使用率",
      "type": "stat"
    },
    {
      "datasource": "Prometheus",
      "fieldConfig": {
        "defaults": {
          "color": {
            "mode": "thresholds"
          },
          "mappings": [],
          "thresholds": {
            "mode": "absolute",
            "steps": [
              {
                "color": "green",
                "value": null
              },
              {
                "color": "yellow",
                "value": 50
              },
              {
                "color": "red",
                "value": 60
              }
            ]
          },
          "unit": "celsius"
        },
        "overrides": []
      },
      "gridPos": {
        "h": 4,
        "w": 6,
        "x": 18,
        "y": 0
      },
      "id": 4,
      "options": {
        "colorMode": "value",
        "graphMode": "area",
        "justifyMode": "auto",
        "orientation": "auto",
        "reduceOptions": {
          "calcs": [
            "lastNotNull"
          ],
          "fields": "",
          "values": false
        },
        "text": {},
        "textMode": "auto"
      },
      "pluginVersion": "8.0.0",
      "targets": [
        {
          "expr": "mtxrHlTemperature{instance=\"192.168.1.1\",job=\"routeros\"} / 10",
          "refId": "A"
        }
      ],
      "title": "システム温度",
      "type": "stat"
    },
    {
      "datasource": "Prometheus",
      "fieldConfig": {
        "defaults": {
          "color": {
            "mode": "thresholds"
          },
          "mappings": [],
          "thresholds": {
            "mode": "absolute",
            "steps": [
              {
                "color": "green",
                "value": null
              },
              {
                "color": "yellow",
                "value": 600
              },
              {
                "color": "red",
                "value": 500
              }
            ]
          },
          "unit": "rothz",
          "decimals": 0
        },
        "overrides": []
      },
      "gridPos": {
        "h": 4,
        "w": 6,
        "x": 18,
        "y": 0
      },
      "id": 28,
      "options": {
        "colorMode": "value",
        "graphMode": "area",
        "justifyMode": "auto",
        "orientation": "auto",
        "reduceOptions": {
          "calcs": [
            "lastNotNull"
          ],
          "fields": "",
          "values": false
        },
        "text": {},
        "textMode": "auto"
      },
      "pluginVersion": "8.5.2",
      "targets": [
        {
          "expr": "mtxrHlCpuFrequency{job=\"routeros\"}",
          "refId": "A"
        }
      ],
      "title": "CPU周波数",
      "type": "stat"
    },
    {
      "datasource": "Prometheus",
      "fieldConfig": {
        "defaults": {
          "color": {
            "mode": "palette-classic"
          },
          "custom": {
            "axisLabel": "",
            "axisPlacement": "auto",
            "barAlignment": 0,
            "drawStyle": "line",
            "fillOpacity": 10,
            "gradientMode": "none",
            "hideFrom": {
              "tooltip": false,
              "viz": false,
              "legend": false
            },
            "lineInterpolation": "linear",
            "lineWidth": 1,
            "pointSize": 5,
            "scaleDistribution": {
              "type": "linear"
            },
            "showPoints": "never",
            "spanNulls": false,
            "stacking": {
              "group": "A",
              "mode": "none"
            },
            "thresholdsStyle": {
              "mode": "off"
            }
          },
          "mappings": [],
          "thresholds": {
            "mode": "absolute",
            "steps": [
              {
                "color": "green",
                "value": null
              }
            ]
          },
          "unit": "bps"
        },
        "overrides": []
      },
      "gridPos": {
        "h": 8,
        "w": 12,
        "x": 0,
        "y": 4
      },
      "id": 5,
      "options": {
        "legend": {
          "calcs": ["mean", "max"],
          "displayMode": "table",
          "placement": "bottom"
        },
        "tooltip": {
          "mode": "multi"
        }
      },
      "pluginVersion": "8.0.0",
      "targets": [
        {
          "expr": "rate(ifInOctets{instance=\"192.168.1.1\",job=\"routeros\",ifDescr!=\"\"}[5m]) * 8",
          "refId": "A",
          "legendFormat": "受信 {{ifDescr}}"
        },
        {
          "expr": "-rate(ifOutOctets{instance=\"192.168.1.1\",job=\"routeros\",ifDescr!=\"\"}[5m]) * 8",
          "refId": "B",
          "legendFormat": "送信 {{ifDescr}}"
        }
      ],
      "title": "ネットワークトラフィック",
      "type": "timeseries"
    },
    {
      "datasource": "Prometheus",
      "fieldConfig": {
        "defaults": {
          "color": {
            "mode": "palette-classic"
          },
          "custom": {
            "axisLabel": "",
            "axisPlacement": "auto",
            "barAlignment": 0,
            "drawStyle": "line",
            "fillOpacity": 10,
            "gradientMode": "none",
            "hideFrom": {
              "tooltip": false,
              "viz": false,
              "legend": false
            },
            "lineInterpolation": "linear",
            "lineWidth": 1,
            "pointSize": 5,
            "scaleDistribution": {
              "type": "linear"
            },
            "showPoints": "never",
            "spanNulls": false,
            "stacking": {
              "group": "A",
              "mode": "none"
            },
            "thresholdsStyle": {
              "mode": "off"
            }
          },
          "mappings": [],
          "thresholds": {
            "mode": "absolute",
            "steps": [
              {
                "color": "green",
                "value": null
              }
            ]
          },
          "unit": "percent"
        },
        "overrides": []
      },
      "gridPos": {
        "h": 8,
        "w": 12,
        "x": 12,
        "y": 4
      },
      "id": 6,
      "options": {
        "legend": {
          "calcs": [],
          "displayMode": "list",
          "placement": "bottom"
        },
        "tooltip": {
          "mode": "single"
        }
      },
      "pluginVersion": "8.0.0",
      "targets": [
        {
          "expr": "avg(hrProcessorLoad{instance=\"192.168.1.1\",job=\"routeros\"})",
          "refId": "A",
          "legendFormat": "CPU使用率"
        }
      ],
      "title": "CPU使用率の推移",
      "type": "timeseries"
    },
    {
      "datasource": "Prometheus",
      "fieldConfig": {
        "defaults": {
          "color": {
            "mode": "palette-classic"
          },
          "custom": {
            "axisLabel": "",
            "axisPlacement": "auto",
            "barAlignment": 0,
            "drawStyle": "line",
            "fillOpacity": 10,
            "gradientMode": "none",
            "hideFrom": {
              "tooltip": false,
              "viz": false,
              "legend": false
            },
            "lineInterpolation": "linear",
            "lineWidth": 1,
            "pointSize": 5,
            "scaleDistribution": {
              "type": "linear"
            },
            "showPoints": "never",
            "spanNulls": false,
            "stacking": {
              "group": "A",
              "mode": "none"
            },
            "thresholdsStyle": {
              "mode": "off"
            }
          },
          "mappings": [],
          "thresholds": {
            "mode": "absolute",
            "steps": [
              {
                "color": "green",
                "value": null
              }
            ]
          },
          "unit": "percent"
        },
        "overrides": []
      },
      "gridPos": {
        "h": 8,
        "w": 12,
        "x": 0,
        "y": 12
      },
      "id": 7,
      "options": {
        "legend": {
          "calcs": [],
          "displayMode": "list",
          "placement": "bottom"
        },
        "tooltip": {
          "mode": "multi"
        }
      },
      "pluginVersion": "8.0.0",
      "targets": [
        {
          "expr": "(hrStorageUsed{instance=\"192.168.1.1\",job=\"routeros\",hrStorageIndex=\"65536\"} / hrStorageSize{instance=\"192.168.1.1\",job=\"routeros\",hrStorageIndex=\"65536\"}) * 100",
          "refId": "A",
          "legendFormat": "メモリ"
        }
      ],
      "title": "メモリ使用率履歴",
      "type": "timeseries"
    },
    {
      "datasource": "Prometheus",
      "fieldConfig": {
        "defaults": {
          "color": {
            "mode": "thresholds"
          },
          "custom": {
            "align": "auto",
            "displayMode": "auto"
          },
          "mappings": [],
          "thresholds": {
            "mode": "absolute",
            "steps": [
              {
                "color": "green",
                "value": null
              }
            ]
          }
        },
        "overrides": [
          {
            "matcher": {
              "id": "byName",
              "options": "状態"
            },
            "properties": [
              {
                "id": "mappings",
                "value": [
                  {
                    "options": {
                      "1": {
                        "color": "green",
                        "index": 0,
                        "text": "UP"
                      },
                      "2": {
                        "color": "red",
                        "index": 1,
                        "text": "DOWN"
                      }
                    },
                    "type": "value"
                  }
                ]
              },
              {
                "id": "custom.displayMode",
                "value": "color-background"
              }
            ]
          },
          {
            "matcher": {
              "id": "byName",
              "options": "速度"
            },
            "properties": [
              {
                "id": "unit",
                "value": "bps"
              }
            ]
          }
        ]
      },
      "gridPos": {
        "h": 8,
        "w": 12,
        "x": 12,
        "y": 12
      },
      "id": 8,
      "options": {
        "showHeader": true,
        "sortBy": []
      },
      "pluginVersion": "8.0.0",
      "targets": [
        {
          "expr": "ifOperStatus{instance=\"192.168.1.1\",job=\"routeros\"}",
          "format": "table",
          "instant": true,
          "refId": "A"
        },
        {
          "expr": "ifSpeed{instance=\"192.168.1.1\",job=\"routeros\"}",
          "format": "table",
          "instant": true,
          "refId": "B"
        },
        {
          "expr": "ifDescr{instance=\"192.168.1.1\",job=\"routeros\"}",
          "format": "table",
          "instant": true,
          "refId": "C"
        }
      ],
      "title": "インターフェース状態",
      "transformations": [
        {
          "id": "seriesToColumns",
          "options": {
            "byField": "ifIndex"
          }
        },
        {
          "id": "organize",
          "options": {
            "excludeByName": {
              "Time": true,
              "Time 1": true,
              "Time 2": true,
              "Time 3": true,
              "__name__": true,
              "__name__ 1": true,
              "__name__ 2": true,
              "__name__ 3": true,
              "instance": true,
              "instance 1": true,
              "instance 2": true,
              "instance 3": true,
              "job": true,
              "job 1": true,
              "job 2": true,
              "job 3": true
            },
            "indexByName": {
              "ifIndex": 0,
              "Value #C": 1,
              "Value #A": 2,
              "Value #B": 3
            },
            "renameByName": {
              "Value #A": "状態",
              "Value #B": "速度",
              "Value #C": "インターフェース名",
              "ifIndex": "Index"
            }
          }
        }
      ],
      "type": "table"
    },
    {
      "datasource": "Prometheus",
      "fieldConfig": {
        "defaults": {
          "color": {
            "mode": "thresholds"
          },
          "mappings": [],
          "thresholds": {
            "mode": "absolute",
            "steps": [
              {
                "color": "green",
                "value": null
              },
              {
                "color": "yellow",
                "value": 0.01
              },
              {
                "color": "red",
                "value": 0.05
              }
            ]
          },
          "unit": "errors/sec"
        },
        "overrides": []
      },
      "gridPos": {
        "h": 8,
        "w": 12,
        "x": 0,
        "y": 20
      },
      "id": 9,
      "options": {
        "legend": {
          "calcs": [],
          "displayMode": "list",
          "placement": "bottom"
        },
        "tooltip": {
          "mode": "multi"
        }
      },
      "pluginVersion": "8.0.0",
      "targets": [
        {
          "expr": "rate(ifInErrors{instance=\"192.168.1.1\",job=\"routeros\"}[5m])",
          "refId": "A",
          "legendFormat": "受信エラー Interface {{ifIndex}}"
        },
        {
          "expr": "rate(ifOutErrors{instance=\"192.168.1.1\",job=\"routeros\"}[5m])",
          "refId": "B",
          "legendFormat": "送信エラー Interface {{ifIndex}}"
        }
      ],
      "title": "インターフェースエラー数/秒",
      "type": "timeseries"
    },
    {
      "datasource": "Prometheus",
      "fieldConfig": {
        "defaults": {
          "color": {
            "mode": "thresholds"
          },
          "mappings": [],
          "thresholds": {
            "mode": "absolute",
            "steps": [
              {
                "color": "green",
                "value": null
              },
              {
                "color": "yellow",
                "value": 70
              },
              {
                "color": "red",
                "value": 85
              }
            ]
          },
          "unit": "percent",
          "min": 0,
          "max": 100
        },
        "overrides": []
      },
      "gridPos": {
        "h": 8,
        "w": 12,
        "x": 12,
        "y": 20
      },
      "id": 10,
      "options": {
        "displayMode": "lcd",
        "orientation": "horizontal",
        "reduceOptions": {
          "calcs": [
            "lastNotNull"
          ],
          "fields": "",
          "values": false
        },
        "showUnfilled": true
      },
      "pluginVersion": "8.0.0",
      "targets": [
        {
          "expr": "(hrStorageUsed{instance=\"192.168.1.1\",job=\"routeros\",hrStorageIndex=\"131072\"} / hrStorageSize{instance=\"192.168.1.1\",job=\"routeros\",hrStorageIndex=\"131072\"}) * 100",
          "refId": "A",
          "legendFormat": "システムディスク"
        }
      ],
      "title": "ディスク使用率",
      "type": "bargauge"
    },
    {
      "datasource": "Prometheus",
      "fieldConfig": {
        "defaults": {
          "color": {
            "mode": "palette-classic"
          },
          "custom": {
            "axisLabel": "",
            "axisPlacement": "auto",
            "barAlignment": 0,
            "drawStyle": "line",
            "fillOpacity": 10,
            "gradientMode": "none",
            "hideFrom": {
              "tooltip": false,
              "viz": false,
              "legend": false
            },
            "lineInterpolation": "linear",
            "lineWidth": 1,
            "pointSize": 5,
            "scaleDistribution": {
              "type": "linear"
            },
            "showPoints": "never",
            "spanNulls": false,
            "stacking": {
              "group": "A",
              "mode": "none"
            },
            "thresholdsStyle": {
              "mode": "off"
            }
          },
          "mappings": [],
          "thresholds": {
            "mode": "absolute",
            "steps": [
              {
                "color": "green",
                "value": null
              }
            ]
          },
          "unit": "celsius"
        },
        "overrides": []
      },
      "gridPos": {
        "h": 8,
        "w": 12,
        "x": 0,
        "y": 28
      },
      "id": 11,
      "options": {
        "legend": {
          "calcs": ["mean", "max"],
          "displayMode": "list",
          "placement": "bottom"
        },
        "tooltip": {
          "mode": "single"
        }
      },
      "pluginVersion": "8.0.0",
      "targets": [
        {
          "expr": "mtxrHlTemperature{instance=\"192.168.1.1\",job=\"routeros\"} / 10",
          "refId": "A",
          "legendFormat": "システム温度"
        },
        {
          "expr": "mtxrHlProcessorTemperature{instance=\"192.168.1.1\",job=\"routeros\"} / 10",
          "refId": "B",
          "legendFormat": "CPU温度"
        }
      ],
      "title": "温度推移",
      "type": "timeseries"
    },
    {
      "datasource": "Prometheus",
      "fieldConfig": {
        "defaults": {
          "color": {
            "mode": "thresholds"
          },
          "mappings": [],
          "thresholds": {
            "mode": "absolute",
            "steps": [
              {
                "color": "green",
                "value": null
              },
              {
                "color": "yellow",
                "value": 10
              },
              {
                "color": "red",
                "value": 13
              }
            ]
          },
          "unit": "volt"
        },
        "overrides": []
      },
      "gridPos": {
        "h": 8,
        "w": 12,
        "x": 12,
        "y": 28
      },
      "id": 12,
      "options": {
        "orientation": "auto",
        "reduceOptions": {
          "calcs": [
            "lastNotNull"
          ],
          "fields": "",
          "values": false
        },
        "showThresholdLabels": false,
        "showThresholdMarkers": true
      },
      "pluginVersion": "8.0.0",
      "targets": [
        {
          "expr": "mtxrHlVoltage{instance=\"192.168.1.1\",job=\"routeros\"} / 10",
          "refId": "A"
        }
      ],
      "title": "システム電圧",
      "type": "gauge"
    },
    {
      "datasource": "Prometheus",
      "fieldConfig": {
        "defaults": {
          "color": {
            "mode": "thresholds"
          },
          "mappings": [
            {
              "options": {
                "1": {
                  "text": "UP",
                  "color": "green"
                },
                "2": {
                  "text": "DOWN",
                  "color": "red"
                }
              },
              "type": "value"
            }
          ],
          "thresholds": {
            "mode": "absolute",
            "steps": [
              {
                "color": "red",
                "value": null
              },
              {
                "color": "green",
                "value": 1
              }
            ]
          }
        },
        "overrides": []
      },
      "gridPos": {
        "h": 4,
        "w": 6,
        "x": 0,
        "y": 36
      },
      "id": 13,
      "options": {
        "colorMode": "background",
        "graphMode": "none",
        "justifyMode": "auto",
        "orientation": "auto",
        "reduceOptions": {
          "calcs": [
            "lastNotNull"
          ],
          "fields": "",
          "values": false
        },
        "text": {},
        "textMode": "auto"
      },
      "pluginVersion": "8.0.0",
      "targets": [
        {
          "expr": "ifOperStatus{instance=\"192.168.1.1\",job=\"routeros\",ifIndex=\"10\"}",
          "refId": "A",
          "legendFormat": "PPPoE接続"
        }
      ],
      "title": "PPPoE接続状態",
      "type": "stat"
    },
    {
      "datasource": "Prometheus",
      "fieldConfig": {
        "defaults": {
          "color": {
            "mode": "thresholds"
          },
          "mappings": [
            {
              "options": {
                "1": {
                  "text": "UP",
                  "color": "green"
                },
                "2": {
                  "text": "DOWN",
                  "color": "red"
                }
              },
              "type": "value"
            }
          ],
          "thresholds": {
            "mode": "absolute",
            "steps": [
              {
                "color": "red",
                "value": null
              },
              {
                "color": "green",
                "value": 1
              }
            ]
          }
        },
        "overrides": []
      },
      "gridPos": {
        "h": 4,
        "w": 6,
        "x": 6,
        "y": 36
      },
      "id": 14,
      "options": {
        "colorMode": "background",
        "graphMode": "none",
        "justifyMode": "auto",
        "orientation": "auto",
        "reduceOptions": {
          "calcs": [
            "lastNotNull"
          ],
          "fields": "",
          "values": false
        },
        "text": {},
        "textMode": "auto"
      },
      "pluginVersion": "8.0.0",
      "targets": [
        {
          "expr": "ifOperStatus{instance=\"192.168.1.1\",job=\"routeros\",ifIndex=\"12\"}",
          "refId": "A",
          "legendFormat": "WireGuard (wg-home)"
        }
      ],
      "title": "WireGuard接続状態",
      "type": "stat"
    },
    {
      "datasource": "Prometheus",
      "fieldConfig": {
        "defaults": {
          "color": {
            "mode": "palette-classic"
          },
          "custom": {
            "axisLabel": "",
            "axisPlacement": "auto",
            "barAlignment": 0,
            "drawStyle": "line",
            "fillOpacity": 10,
            "gradientMode": "none",
            "hideFrom": {
              "tooltip": false,
              "viz": false,
              "legend": false
            },
            "lineInterpolation": "linear",
            "lineWidth": 1,
            "pointSize": 5,
            "scaleDistribution": {
              "type": "linear"
            },
            "showPoints": "never",
            "spanNulls": false,
            "stacking": {
              "group": "A",
              "mode": "none"
            },
            "thresholdsStyle": {
              "mode": "off"
            }
          },
          "mappings": [],
          "thresholds": {
            "mode": "absolute",
            "steps": [
              {
                "color": "green",
                "value": null
              }
            ]
          },
          "unit": "bps"
        },
        "overrides": []
      },
      "gridPos": {
        "h": 8,
        "w": 12,
        "x": 12,
        "y": 36
      },
      "id": 15,
      "options": {
        "legend": {
          "calcs": [],
          "displayMode": "list",
          "placement": "bottom"
        },
        "tooltip": {
          "mode": "multi"
        }
      },
      "pluginVersion": "8.0.0",
      "targets": [
        {
          "expr": "rate(ifOutOctets{instance=\"192.168.1.1\",job=\"routeros\",ifIndex=\"12\"}[5m]) * 8",
          "refId": "A",
          "legendFormat": "WireGuard送信"
        }
      ],
      "title": "WireGuardトラフィック（送信のみ）",
      "description": "注: RouterOSの制限により、WireGuard受信トラフィックは正しく計測されません",
      "type": "timeseries"
    },
    {
      "datasource": "Prometheus",
      "fieldConfig": {
        "defaults": {
          "color": {
            "mode": "thresholds"
          },
          "mappings": [],
          "thresholds": {
            "mode": "absolute",
            "steps": [
              {
                "color": "green",
                "value": null
              },
              {
                "color": "yellow",
                "value": 10
              },
              {
                "color": "red",
                "value": 20
              }
            ]
          },
          "unit": "short"
        },
        "overrides": []
      },
      "gridPos": {
        "h": 4,
        "w": 6,
        "x": 0,
        "y": 32
      },
      "id": 17,
      "options": {
        "colorMode": "value",
        "graphMode": "area",
        "justifyMode": "auto",
        "orientation": "auto",
        "reduceOptions": {
          "calcs": [
            "lastNotNull"
          ],
          "fields": "",
          "values": false
        },
        "text": {},
        "textMode": "auto"
      },
      "pluginVersion": "8.0.0",
      "targets": [
        {
          "expr": "mtxrDHCPLeaseCount{instance=\"192.168.1.1\",job=\"routeros\"}",
          "refId": "A"
        }
      ],
      "title": "アクティブDHCPリース数",
      "description": "現在割り当てられているDHCPリースの数",
      "type": "stat"
    },
    {
      "datasource": "Prometheus",
      "fieldConfig": {
        "defaults": {
          "color": {
            "mode": "thresholds"
          },
          "mappings": [],
          "thresholds": {
            "mode": "absolute",
            "steps": [
              {
                "color": "green",
                "value": null
              },
              {
                "color": "red",
                "value": 1
              }
            ]
          },
          "unit": "short"
        },
        "overrides": []
      },
      "gridPos": {
        "h": 4,
        "w": 6,
        "x": 6,
        "y": 32
      },
      "id": 18,
      "options": {
        "colorMode": "value",
        "graphMode": "area",
        "justifyMode": "auto",
        "orientation": "auto",
        "reduceOptions": {
          "calcs": [
            "lastNotNull"
          ],
          "fields": "",
          "values": false
        },
        "text": {},
        "textMode": "auto"
      },
      "pluginVersion": "8.0.0",
      "targets": [
        {
          "expr": "mtxrSystemRebootCount{instance=\"192.168.1.1\",job=\"routeros\"}",
          "refId": "A"
        }
      ],
      "title": "システム再起動回数",
      "description": "システムが再起動した累計回数",
      "type": "stat"
    },
    {
      "datasource": "Prometheus",
      "fieldConfig": {
        "defaults": {
          "color": {
            "mode": "thresholds"
          },
          "mappings": [],
          "thresholds": {
            "mode": "absolute",
            "steps": [
              {
                "color": "green",
                "value": null
              },
              {
                "color": "red",
                "value": 1
              }
            ]
          },
          "unit": "short"
        },
        "overrides": []
      },
      "gridPos": {
        "h": 4,
        "w": 6,
        "x": 12,
        "y": 32
      },
      "id": 19,
      "options": {
        "colorMode": "value",
        "graphMode": "area",
        "justifyMode": "auto",
        "orientation": "auto",
        "reduceOptions": {
          "calcs": [
            "lastNotNull"
          ],
          "fields": "",
          "values": false
        },
        "text": {},
        "textMode": "auto"
      },
      "pluginVersion": "8.0.0",
      "targets": [
        {
          "expr": "mtxrSystemBadBlocks{instance=\"192.168.1.1\",job=\"routeros\"}",
          "refId": "A"
        }
      ],
      "title": "不良ブロック数",
      "description": "メモリ内の不良ブロック数",
      "type": "stat"
    },
    {
      "datasource": "Prometheus",
      "fieldConfig": {
        "defaults": {
          "color": {
            "mode": "thresholds"
          },
          "mappings": [],
          "thresholds": {
            "mode": "absolute",
            "steps": [
              {
                "color": "green",
                "value": null
              },
              {
                "color": "red",
                "value": 1
              }
            ]
          },
          "unit": "short"
        },
        "overrides": []
      },
      "gridPos": {
        "h": 4,
        "w": 6,
        "x": 18,
        "y": 32
      },
      "id": 20,
      "options": {
        "colorMode": "value",
        "graphMode": "area",
        "justifyMode": "auto",
        "orientation": "auto",
        "reduceOptions": {
          "calcs": [
            "lastNotNull"
          ],
          "fields": "",
          "values": false
        },
        "text": {},
        "textMode": "auto"
      },
      "pluginVersion": "8.0.0",
      "targets": [
        {
          "expr": "mtxrSystemUSBPowerResets{instance=\"192.168.1.1\",job=\"routeros\"}",
          "refId": "A"
        }
      ],
      "title": "USB電源リセット回数",
      "description": "USB電源がリセットされた累計回数",
      "type": "stat"
    },
    {
      "datasource": "Prometheus",
      "fieldConfig": {
        "defaults": {
          "color": {
            "mode": "thresholds"
          },
          "mappings": [],
          "thresholds": {
            "mode": "absolute",
            "steps": [
              {
                "color": "text",
                "value": null
              }
            ]
          },
          "unit": "none"
        },
        "overrides": [
          {
            "matcher": {
              "id": "byName",
              "options": "192.168.1.1"
            },
            "properties": [
              {
                "id": "displayName",
                "value": "${__field.labels.mtxrSystemCurrentVersion}"
              }
            ]
          }
        ]
      },
      "gridPos": {
        "h": 4,
        "w": 6,
        "x": 0,
        "y": 36
      },
      "id": 21,
      "options": {
        "colorMode": "none",
        "graphMode": "none",
        "justifyMode": "auto",
        "orientation": "auto",
        "reduceOptions": {
          "calcs": [
            "lastNotNull"
          ],
          "fields": "",
          "values": false
        },
        "text": {},
        "textMode": "name"
      },
      "pluginVersion": "8.0.0",
      "targets": [
        {
          "expr": "mtxrSystemCurrentVersion{instance=\"192.168.1.1\",job=\"routeros\"}",
          "refId": "A",
          "legendFormat": "{{mtxrSystemCurrentVersion}}"
        }
      ],
      "title": "現在のバージョン",
      "description": "インストールされているRouterOSのバージョン",
      "type": "stat"
    },
    {
      "datasource": "Prometheus",
      "fieldConfig": {
        "defaults": {
          "color": {
            "mode": "thresholds"
          },
          "mappings": [],
          "thresholds": {
            "mode": "absolute",
            "steps": [
              {
                "color": "text",
                "value": null
              }
            ]
          },
          "unit": "none"
        },
        "overrides": [
          {
            "matcher": {
              "id": "byName",
              "options": "7.19.2"
            },
            "properties": [
              {
                "id": "displayName",
                "value": "${__field.labels.mtxrSystemUpgradeVersion}"
              }
            ]
          }
        ]
      },
      "gridPos": {
        "h": 4,
        "w": 6,
        "x": 6,
        "y": 36
      },
      "id": 23,
      "options": {
        "colorMode": "none",
        "graphMode": "none",
        "justifyMode": "auto",
        "orientation": "auto",
        "reduceOptions": {
          "calcs": [
            "lastNotNull"
          ],
          "fields": "",
          "values": false
        },
        "text": {},
        "textMode": "name"
      },
      "pluginVersion": "8.0.0",
      "targets": [
        {
          "expr": "mtxrSystemUpgradeVersion{instance=\"192.168.1.1\",job=\"routeros\"}",
          "refId": "A",
          "legendFormat": "{{mtxrSystemUpgradeVersion}}"
        }
      ],
      "title": "利用可能なアップグレード",
      "description": "アップグレード可能なRouterOSのバージョン",
      "type": "stat"
    },
    {
      "datasource": "Prometheus",
      "fieldConfig": {
        "defaults": {
          "color": {
            "mode": "palette-classic"
          },
          "custom": {
            "axisLabel": "",
            "axisPlacement": "auto",
            "barAlignment": 0,
            "drawStyle": "line",
            "fillOpacity": 10,
            "gradientMode": "none",
            "hideFrom": {
              "legend": false,
              "tooltip": false,
              "viz": false
            },
            "lineInterpolation": "linear",
            "lineWidth": 1,
            "pointSize": 5,
            "scaleDistribution": {
              "type": "linear"
            },
            "showPoints": "never",
            "spanNulls": true,
            "stacking": {
              "group": "A",
              "mode": "none"
            },
            "thresholdsStyle": {
              "mode": "off"
            }
          },
          "mappings": [],
          "thresholds": {
            "mode": "absolute",
            "steps": [
              {
                "color": "green",
                "value": null
              }
            ]
          },
          "unit": "short"
        },
        "overrides": []
      },
      "gridPos": {
        "h": 8,
        "w": 12,
        "x": 12,
        "y": 36
      },
      "id": 22,
      "options": {
        "legend": {
          "calcs": [],
          "displayMode": "list",
          "placement": "bottom"
        },
        "tooltip": {
          "mode": "multi"
        }
      },
      "pluginVersion": "8.0.0",
      "targets": [
        {
          "expr": "mtxrDHCPLeaseCount{instance=\"192.168.1.1\",job=\"routeros\"}",
          "refId": "A",
          "legendFormat": "DHCPリース数"
        }
      ],
      "title": "DHCPリース数推移",
      "description": "時間経過によるDHCPリース数の変化",
      "type": "timeseries"
    },
    {
      "datasource": "Prometheus",
      "fieldConfig": {
        "defaults": {
          "color": {
            "mode": "palette-classic"
          },
          "custom": {
            "axisLabel": "",
            "axisPlacement": "auto",
            "barAlignment": 0,
            "drawStyle": "line",
            "fillOpacity": 10,
            "gradientMode": "none",
            "hideFrom": {
              "legend": false,
              "tooltip": false,
              "viz": false
            },
            "lineInterpolation": "linear",
            "lineWidth": 1,
            "pointSize": 5,
            "scaleDistribution": {
              "type": "linear"
            },
            "showPoints": "never",
            "spanNulls": true,
            "stacking": {
              "group": "A",
              "mode": "none"
            },
            "thresholdsStyle": {
              "mode": "off"
            }
          },
          "mappings": [],
          "thresholds": {
            "mode": "absolute",
            "steps": [
              {
                "color": "green",
                "value": null
              }
            ]
          },
          "unit": "pps"
        },
        "overrides": []
      },
      "gridPos": {
        "h": 8,
        "w": 12,
        "x": 0,
        "y": 44
      },
      "id": 24,
      "options": {
        "legend": {
          "calcs": ["lastNotNull", "max"],
          "displayMode": "table",
          "placement": "bottom"
        },
        "tooltip": {
          "mode": "multi"
        }
      },
      "pluginVersion": "8.0.0",
      "targets": [
        {
          "expr": "rate(mtxrInterfaceRxDrop{instance=\"192.168.1.1\",job=\"routeros\",mtxrInterfaceName=~\"ether1|pppoe-out1|wg-home|sfp1\"}[5m])",
          "refId": "A",
          "legendFormat": "Rx Drop - {{mtxrInterfaceName}}"
        },
        {
          "expr": "rate(mtxrInterfaceTxDrop{instance=\"192.168.1.1\",job=\"routeros\",mtxrInterfaceName=~\"ether1|pppoe-out1|wg-home|sfp1\"}[5m])",
          "refId": "B",
          "legendFormat": "Tx Drop - {{mtxrInterfaceName}}"
        }
      ],
      "title": "パケットドロップ率",
      "description": "主要インターフェースのパケットドロップ率",
      "type": "timeseries"
    },
    {
      "datasource": "Prometheus",
      "fieldConfig": {
        "defaults": {
          "color": {
            "mode": "thresholds"
          },
          "mappings": [],
          "thresholds": {
            "mode": "absolute",
            "steps": [
              {
                "color": "green",
                "value": null
              },
              {
                "color": "yellow",
                "value": 1000000
              },
              {
                "color": "red",
                "value": 10000000
              }
            ]
          },
          "unit": "short"
        },
        "overrides": []
      },
      "gridPos": {
        "h": 8,
        "w": 12,
        "x": 12,
        "y": 44
      },
      "id": 25,
      "options": {
        "displayMode": "lcd",
        "orientation": "horizontal",
        "reduceOptions": {
          "calcs": [
            "lastNotNull"
          ],
          "fields": "",
          "values": false
        },
        "showUnfilled": true
      },
      "pluginVersion": "8.0.0",
      "targets": [
        {
          "expr": "mtxrInterfaceRxDrop{instance=\"192.168.1.1\",job=\"routeros\"}",
          "refId": "A",
          "legendFormat": "Rx Drop - {{mtxrInterfaceName}}"
        },
        {
          "expr": "mtxrInterfaceTxDrop{instance=\"192.168.1.1\",job=\"routeros\"}",
          "refId": "B",
          "legendFormat": "Tx Drop - {{mtxrInterfaceName}}"
        }
      ],
      "title": "累計パケットドロップ数",
      "description": "インターフェース別の累計パケットドロップ数",
      "type": "bargauge"
    },
    {
      "datasource": "Prometheus",
      "fieldConfig": {
        "defaults": {
          "color": {
            "mode": "thresholds"
          },
          "mappings": [],
          "thresholds": {
            "mode": "absolute",
            "steps": [
              {
                "color": "text",
                "value": null
              }
            ]
          }
        },
        "overrides": []
      },
      "gridPos": {
        "h": 4,
        "w": 4,
        "x": 0,
        "y": 32
      },
      "id": 29,
      "options": {
        "colorMode": "none",
        "graphMode": "none",
        "justifyMode": "auto",
        "orientation": "horizontal",
        "reduceOptions": {
          "calcs": [
            "lastNotNull"
          ],
          "fields": "",
          "values": false
        },
        "text": {},
        "textMode": "name"
      },
      "pluginVersion": "8.5.2",
      "targets": [
        {
          "expr": "mtxrSystemSerialNumber{job=\"routeros\"}",
          "legendFormat": "{{mtxrSystemSerialNumber}}",
          "refId": "A"
        }
      ],
      "title": "シリアル番号",
      "type": "stat"
    },
    {
      "datasource": "Prometheus",
      "fieldConfig": {
        "defaults": {
          "color": {
            "mode": "thresholds"
          },
          "mappings": [],
          "thresholds": {
            "mode": "absolute",
            "steps": [
              {
                "color": "text",
                "value": null
              }
            ]
          }
        },
        "overrides": []
      },
      "gridPos": {
        "h": 4,
        "w": 4,
        "x": 4,
        "y": 32
      },
      "id": 30,
      "options": {
        "colorMode": "none",
        "graphMode": "none",
        "justifyMode": "auto",
        "orientation": "horizontal",
        "reduceOptions": {
          "calcs": [
            "lastNotNull"
          ],
          "fields": "",
          "values": false
        },
        "text": {},
        "textMode": "name"
      },
      "pluginVersion": "8.5.2",
      "targets": [
        {
          "expr": "mtxrSystemBoardName{job=\"routeros\"}",
          "legendFormat": "{{mtxrSystemBoardName}}",
          "refId": "A"
        }
      ],
      "title": "ボード名",
      "type": "stat"
    },
    {
      "datasource": "Prometheus",
      "fieldConfig": {
        "defaults": {
          "color": {
            "mode": "thresholds"
          },
          "mappings": [],
          "thresholds": {
            "mode": "absolute",
            "steps": [
              {
                "color": "text",
                "value": null
              }
            ]
          }
        },
        "overrides": []
      },
      "gridPos": {
        "h": 4,
        "w": 4,
        "x": 8,
        "y": 32
      },
      "id": 31,
      "options": {
        "colorMode": "none",
        "graphMode": "none",
        "justifyMode": "auto",
        "orientation": "horizontal",
        "reduceOptions": {
          "calcs": [
            "lastNotNull"
          ],
          "fields": "",
          "values": false
        },
        "text": {},
        "textMode": "name"
      },
      "pluginVersion": "8.5.2",
      "targets": [
        {
          "expr": "mtxrSystemModel{job=\"routeros\"}",
          "legendFormat": "{{mtxrSystemModel}}",
          "refId": "A"
        }
      ],
      "title": "モデル名", 
      "type": "stat"
    },
    {
      "datasource": "Prometheus",
      "fieldConfig": {
        "defaults": {
          "custom": {
            "align": "auto",
            "displayMode": "auto"
          },
          "mappings": [],
          "thresholds": {
            "mode": "absolute",
            "steps": [
              {
                "color": "green",
                "value": null
              }
            ]
          }
        },
        "overrides": [
          {
            "matcher": {
              "id": "byName",
              "options": "アクティブ"
            },
            "properties": [
              {
                "id": "mappings",
                "value": [
                  {
                    "options": {
                      "0": {
                        "color": "gray",
                        "index": 0,
                        "text": "非アクティブ"
                      },
                      "1": {
                        "color": "green",
                        "index": 1,
                        "text": "アクティブ"
                      }
                    },
                    "type": "value"
                  }
                ]
              },
              {
                "id": "custom.displayMode",
                "value": "color-background"
              }
            ]
          },
          {
            "matcher": {
              "id": "byName",
              "options": "実行中"
            },
            "properties": [
              {
                "id": "mappings",
                "value": [
                  {
                    "options": {
                      "0": {
                        "color": "gray",
                        "index": 0,
                        "text": "停止"
                      },
                      "1": {
                        "color": "green",
                        "index": 1,
                        "text": "実行中"
                      }
                    },
                    "type": "value"
                  }
                ]
              },
              {
                "id": "custom.displayMode",
                "value": "color-background"
              }
            ]
          },
          {
            "matcher": {
              "id": "byName",
              "options": "サイズ (MB)"
            },
            "properties": [
              {
                "id": "unit",
                "value": "decmbytes"
              }
            ]
          }
        ]
      },
      "gridPos": {
        "h": 8,
        "w": 12,
        "x": 0,
        "y": 40
      },
      "id": 32,
      "options": {
        "showHeader": true,
        "sortBy": []
      },
      "pluginVersion": "8.5.2",
      "targets": [
        {
          "expr": "mtxrPartitionName{job=\"routeros\"}",
          "format": "table",
          "instant": true,
          "refId": "A"
        },
        {
          "expr": "mtxrPartitionSize{job=\"routeros\"}",
          "format": "table",
          "instant": true,
          "refId": "B"
        },
        {
          "expr": "mtxrPartitionVersion{job=\"routeros\"}",
          "format": "table",
          "instant": true,
          "refId": "C"
        },
        {
          "expr": "mtxrPartitionActive{job=\"routeros\"}",
          "format": "table",
          "instant": true,
          "refId": "D"
        },
        {
          "expr": "mtxrPartitionRunning{job=\"routeros\"}",
          "format": "table",
          "instant": true,
          "refId": "E"
        }
      ],
      "title": "パーティション情報",
      "transformations": [
        {
          "id": "seriesToColumns",
          "options": {
            "byField": "mtxrPartitionIndex"
          }
        },
        {
          "id": "organize",
          "options": {
            "excludeByName": {
              "Time": true,
              "Time 1": true,
              "Time 2": true,
              "Time 3": true,
              "Time 4": true,
              "Time 5": true,
              "__name__": true,
              "__name__ 1": true,
              "__name__ 2": true,
              "__name__ 3": true,
              "__name__ 4": true,
              "__name__ 5": true,
              "instance": true,
              "instance 1": true,
              "instance 2": true,
              "instance 3": true,
              "instance 4": true,
              "instance 5": true,
              "job": true,
              "job 1": true,
              "job 2": true,
              "job 3": true,
              "job 4": true,
              "job 5": true
            },
            "indexByName": {
              "mtxrPartitionIndex": 0,
              "Value #A": 1,
              "Value #B": 2,
              "Value #C": 3,
              "Value #D": 4,
              "Value #E": 5
            },
            "renameByName": {
              "mtxrPartitionIndex": "Index",
              "Value #A": "パーティション名",
              "Value #B": "サイズ (MB)",
              "Value #C": "バージョン",
              "Value #D": "アクティブ",
              "Value #E": "実行中"
            }
          }
        }
      ],
      "type": "table",
      "description": "RouterOSファームウェアパーティションの状態"
    },
    {
      "datasource": "Prometheus",
      "fieldConfig": {
        "defaults": {
          "color": {
            "mode": "thresholds"
          },
          "mappings": [],
          "thresholds": {
            "mode": "absolute",
            "steps": [
              {
                "color": "green",
                "value": null
              },
              {
                "color": "yellow",
                "value": 100
              },
              {
                "color": "red",
                "value": 200
              }
            ]
          },
          "unit": "none"
        },
        "overrides": []
      },
      "gridPos": {
        "h": 4,
        "w": 6,
        "x": 12,
        "y": 40
      },
      "id": 33,
      "options": {
        "colorMode": "value",
        "graphMode": "none",
        "justifyMode": "auto",
        "orientation": "horizontal",
        "reduceOptions": {
          "calcs": [
            "lastNotNull"
          ],
          "fields": "",
          "values": false
        },
        "text": {},
        "textMode": "auto"
      },
      "pluginVersion": "8.5.2",
      "targets": [
        {
          "expr": "count by (instance) (ifOperStatus{job=\"routeros\"} == 1)",
          "refId": "A"
        }
      ],
      "title": "アクティブインターフェース数",
      "description": "稼働中のネットワークインターフェース数",
      "type": "stat"
    },
    {
      "datasource": "Prometheus",
      "fieldConfig": {
        "defaults": {
          "color": {
            "mode": "palette-classic"
          },
          "custom": {
            "axisLabel": "",
            "axisPlacement": "auto",
            "barAlignment": 0,
            "drawStyle": "line",
            "fillOpacity": 10,
            "gradientMode": "none",
            "hideFrom": {
              "tooltip": false,
              "viz": false,
              "legend": false
            },
            "lineInterpolation": "linear",
            "lineWidth": 1,
            "pointSize": 5,
            "scaleDistribution": {
              "type": "linear"
            },
            "showPoints": "never",
            "spanNulls": false,
            "stacking": {
              "group": "A",
              "mode": "none"
            },
            "thresholdsStyle": {
              "mode": "area"
            }
          },
          "mappings": [],
          "thresholds": {
            "mode": "absolute",
            "steps": [
              {
                "color": "green",
                "value": null
              },
              {
                "color": "yellow",
                "value": 50
              },
              {
                "color": "red",
                "value": 80
              }
            ]
          },
          "unit": "percent",
          "min": 0,
          "max": 100
        },
        "overrides": []
      },
      "gridPos": {
        "h": 8,
        "w": 12,
        "x": 0,
        "y": 52
      },
      "id": 40,
      "options": {
        "legend": {
          "calcs": ["mean", "max"],
          "displayMode": "table",
          "placement": "bottom"
        },
        "tooltip": {
          "mode": "multi"
        }
      },
      "pluginVersion": "8.5.2",
      "targets": [
        {
          "expr": "(rate(ifInOctets{job=\"routeros\"}[5m]) * 8 * on(ifIndex) group_left(ifDescr) ifDescr{job=\"routeros\"} / on(ifIndex) ifSpeed{job=\"routeros\"}) * 100",
          "refId": "A",
          "legendFormat": "受信 {{ifDescr}}"
        },
        {
          "expr": "(rate(ifOutOctets{job=\"routeros\"}[5m]) * 8 * on(ifIndex) group_left(ifDescr) ifDescr{job=\"routeros\"} / on(ifIndex) ifSpeed{job=\"routeros\"}) * 100",
          "refId": "B",
          "legendFormat": "送信 {{ifDescr}}"
        }
      ],
      "title": "インターフェース帯域使用率",
      "description": "各インターフェースの帯域使用率（%）",
      "type": "timeseries"
    },
    {
      "datasource": "Prometheus",
      "fieldConfig": {
        "defaults": {
          "color": {
            "mode": "thresholds"
          },
          "mappings": [],
          "thresholds": {
            "mode": "absolute",
            "steps": [
              {
                "color": "green",
                "value": null
              },
              {
                "color": "yellow",
                "value": 1
              },
              {
                "color": "red",
                "value": 5
              }
            ]
          },
          "unit": "none"
        },
        "overrides": []
      },
      "gridPos": {
        "h": 8,
        "w": 24,
        "x": 0,
        "y": 52
      },
      "id": 42,
      "options": {
        "colorMode": "background",
        "graphMode": "none",
        "justifyMode": "center",
        "orientation": "auto",
        "reduceOptions": {
          "calcs": [
            "lastNotNull"
          ],
          "fields": "",
          "values": false
        },
        "text": {
          "titleSize": 14,
          "valueSize": 20
        },
        "textMode": "auto"
      },
      "pluginVersion": "8.5.2",
      "targets": [
        {
          "expr": "mtxrSystemRebootCount{job=\"routeros\"}",
          "refId": "A",
          "legendFormat": "再起動回数"
        },
        {
          "expr": "mtxrSystemBadBlocks{job=\"routeros\"}",
          "refId": "B",
          "legendFormat": "不良ブロック数"
        },
        {
          "expr": "mtxrSystemUSBPowerResets{job=\"routeros\"}",
          "refId": "C",
          "legendFormat": "USB電源リセット回数"
        },
        {
          "expr": "up{job=\"routeros\"}",
          "refId": "D",
          "legendFormat": "稼働状態"
        }
      ],
      "title": "システムヘルスサマリー",
      "description": "RouterOSシステムの健全性指標",
      "type": "stat"
    },
    {
      "datasource": "Loki",
      "fieldConfig": {
        "defaults": {},
        "overrides": []
      },
      "gridPos": {
        "h": 12,
        "w": 24,
        "x": 0,
        "y": 60
      },
      "id": 43,
      "options": {
        "showTime": true,
        "showLabels": true,
        "showCommonLabels": true,
        "wrapLogMessage": false,
        "sortOrder": "Descending",
        "dedupStrategy": "none",
        "enableLogDetails": true
      },
      "targets": [
        {
          "expr": "{job=\"routeros\"}",
          "refId": "A"
        }
      ],
      "title": "RouterOSログ",
      "description": "RouterOSからのsyslogメッセージ",
      "type": "logs"
    },
    {
      "datasource": "Loki",
      "fieldConfig": {
        "defaults": {
          "color": {
            "mode": "palette-classic"
          },
          "custom": {
            "axisLabel": "",
            "axisPlacement": "auto",
            "barAlignment": 0,
            "drawStyle": "line",
            "fillOpacity": 10,
            "gradientMode": "none",
            "hideFrom": {
              "tooltip": false,
              "viz": false,
              "legend": false
            },
            "lineInterpolation": "linear",
            "lineWidth": 1,
            "pointSize": 5,
            "scaleDistribution": {
              "type": "linear"
            },
            "showPoints": "never",
            "spanNulls": false,
            "stacking": {
              "group": "A",
              "mode": "none"
            },
            "thresholdsStyle": {
              "mode": "off"
            }
          },
          "mappings": [],
          "thresholds": {
            "mode": "absolute",
            "steps": [
              {
                "color": "green",
                "value": null
              }
            ]
          },
          "unit": "logs/s"
        },
        "overrides": []
      },
      "gridPos": {
        "h": 8,
        "w": 12,
        "x": 0,
        "y": 72
      },
      "id": 44,
      "options": {
        "legend": {
          "calcs": ["mean", "max"],
          "displayMode": "table",
          "placement": "bottom"
        },
        "tooltip": {
          "mode": "multi"
        }
      },
      "targets": [
        {
          "expr": "sum(rate({job=\"routeros\", level=~\"error|critical\"}[5m])) by (level)",
          "refId": "A",
          "legendFormat": "{{level}}"
        },
        {
          "expr": "sum(rate({job=\"routeros\", level=\"warning\"}[5m])) by (level)",
          "refId": "B",
          "legendFormat": "warning"
        }
      ],
      "title": "エラー/警告ログレート",
      "description": "RouterOSのエラーと警告ログの発生レート",
      "type": "timeseries"
    },
    {
      "datasource": "Loki",
      "fieldConfig": {
        "defaults": {
          "color": {
            "mode": "palette-classic"
          },
          "custom": {
            "axisLabel": "",
            "axisPlacement": "auto",
            "barAlignment": 0,
            "drawStyle": "bars",
            "fillOpacity": 100,
            "gradientMode": "none",
            "hideFrom": {
              "tooltip": false,
              "viz": false,
              "legend": false
            },
            "lineInterpolation": "linear",
            "lineWidth": 1,
            "pointSize": 5,
            "scaleDistribution": {
              "type": "linear"
            },
            "showPoints": "never",
            "spanNulls": false,
            "stacking": {
              "group": "A",
              "mode": "normal"
            },
            "thresholdsStyle": {
              "mode": "off"
            }
          },
          "mappings": [],
          "thresholds": {
            "mode": "absolute",
            "steps": [
              {
                "color": "green",
                "value": null
              }
            ]
          },
          "unit": "logs"
        },
        "overrides": []
      },
      "gridPos": {
        "h": 8,
        "w": 12,
        "x": 12,
        "y": 72
      },
      "id": 45,
      "options": {
        "legend": {
          "calcs": ["sum"],
          "displayMode": "table",
          "placement": "bottom"
        },
        "tooltip": {
          "mode": "multi"
        }
      },
      "targets": [
        {
          "expr": "sum(count_over_time({job=\"routeros\"}[5m])) by (ident)",
          "refId": "A",
          "legendFormat": "{{ident}}"
        }
      ],
      "title": "トピック別ログ分布",
      "description": "RouterOSログのトピック別集計（identフィールド使用）",
      "type": "timeseries"
    }
  ],
  "schemaVersion": 27,
  "style": "dark",
  "tags": ["routeros", "snmp", "network", "mikrotik", "monitoring"],
  "templating": {
    "list": []
  },
  "time": {
    "from": "now-6h",
    "to": "now"
  },
  "timepicker": {},
  "timezone": "",
  "title": "RouterOS 監視ダッシュボード",
  "description": "MikroTik RouterOSの詳細な監視ダッシュボード",
  "uid": "routeros",
  "version": 0
}